gp_api/__init__.py
gp_api/__version__.py
gp_api/gaussian_process.py
gp_api/marginals.py
gp_api/kernels/__init__.py
gp_api/kernels/_compact_kernel.cpython-313-x86_64-linux-musl.so
gp_api/kernels/compact_kernel.py
gp_api/kernels/compact_kernel_evaluate.py
gp_api/kernels/kernels.py
gp_api/kernels/matern_kernel_evaluate.py
gp_api/utils/__init__.py
gp_api/utils/fit_compact.py
gp_api/utils/fit_matern.py
gp_api/utils/hypercube.py
gp_api/utils/multigauss.py
gp_api/utils/utils.py
gaussian_process_api-0.6.0.dist-info/METADATA
gaussian_process_api-0.6.0.dist-info/WHEEL
gaussian_process_api-0.6.0.dist-info/RECORD
