Metadata-Version: 2.1
Name: gaussian_process_api
Version: 0.6.0
Summary: Gaussian process code with C compiled kernel functions that have sparse matrix support
Keywords: astronomy,information analysis,machine learning,physics
Author: D. Wysocki, R. O'Shaughnessy
Author-Email: "V. Delfavero" <xevra86@gmail.com>
Maintainer-Email: "V. Delfavero" <xevra86@gmail.com>
License: MIT License
Classifier: Development Status :: 3 - Alpha
Classifier: Programming Language :: Python :: 3
Classifier: Operating System :: OS Independent
Classifier: Intended Audience :: Science/Research
Classifier: Topic :: Scientific/Engineering :: Astronomy
Classifier: Topic :: Scientific/Engineering :: Physics
Classifier: Topic :: Scientific/Engineering :: Information Analysis
Project-URL: Homepage, https://gitlab.com/xevra/basil-core
Project-URL: Bug tracker, https://gitlab.com/xevra/basil-core/issues
Requires-Python: >=3.12
Requires-Dist: h5py>=2.7.0
Requires-Dist: numpy>=1.21.6
Requires-Dist: matplotlib>=2.0.0
Requires-Dist: scipy>=1.2.0
Requires-Dist: six>=1.10.0
Requires-Dist: scikit-sparse>=0.4.0
Requires-Dist: fast_histogram>=0.10
Requires-Dist: astropy
